hypermediachannels/__init__.py
hypermediachannels/fields.py
hypermediachannels/serializers.py
hypermediachannels-0.0.5.dist-info/METADATA
hypermediachannels-0.0.5.dist-info/RECORD
hypermediachannels-0.0.5.dist-info/WHEEL
hypermediachannels-0.0.5.dist-info/top_level.txt
