Metadata-Version: 2.1
Name: hypermediachannels
Version: 0.0.5
Summary: Hyper Media Channels Rest Framework.
Home-page: https://github.com/hishnash/hypermediachannels
Author: Matthaus Woolard
Author-email: matthaus.woolard@gmail.com
License: MIT
Platform: UNKNOWN
Classifier: Programming Language :: Python :: 3.6
Classifier: Programming Language :: Python :: 3.7
Provides-Extra: tests
Requires-Dist: channels (>=2.1.1)
Requires-Dist: Django (>=2.11)
Requires-Dist: djangochannelsrestframework (~=0.0.6)
Requires-Dist: channelsmultiplexer (~=0.0.2)
Provides-Extra: tests
Requires-Dist: pytest (~=3.7.1); extra == 'tests'
Requires-Dist: pytest-django (~=3.4.1); extra == 'tests'
Requires-Dist: pytest-asyncio (~=0.9); extra == 'tests'
Requires-Dist: coverage (~=4.4); extra == 'tests'
